{"dump_time": "Wed Sep 20 09:32:55 2023", "time_start": "Wed Sep 20 08:50:13 2023", "time_end": "Wed Sep 20 08:50:13 2023", "additional_data": {"name": "calibrationtemp30_ID:525771256544952_SID:0_MAG:NOT_SPECIFIED.mag.json", "SENSOR_SERIAL_DEVICE_PATH": "/dev/cu.usbmodem3867315334391", "SENSOR_SERIAL_NAME": "Unified Sensor 386731533439", "CONFIG_NAME": "", "READING_PREFIX": "calibrationtemp30", "READING_OUTPUT_FOLDER": "/Users/marcelochsendorf/Downloads/MagneticReadoutProcessing/src/MagneticReadoutProcessing/cli/", "READING_DATAPOINT_COUNT": "100", "READING_AVERAGE_COUNT": "20", "READING_MAGNET_TYPE": "0", "configname": "testcfg", "runner": "cli", "sensor_capabilities": "['static', 'axis_b', 'axis_x', 'axis_y', 'axis_z', 'axis_temp', 'axis_stimestamp']", "export_filepath": "/Users/marcelochsendorf/Downloads/MagneticReadoutProcessing/src/MagneticReadoutProcessing/cli//calibrationtemp30_ID:525771256544952_SID:0_MAG:NOT_SPECIFIED.mag.json", "export_filename": "calibrationtemp30_ID:525771256544952_SID:0_MAG:NOT_SPECIFIED.mag.json"}, "data": [{"value": 0.135, "phi": null, "theta": null, "reading_index_phi": null, "reading_index_theta": null, "is_valid": true, "id": 0, "temperature": 34.32000000000001}, {"value": 0.16600000000000004, "phi": null, "theta": null, "reading_index_phi": null, "reading_index_theta": null, "is_valid": true, "id": 1, "temperature": 34.705000000000005}, {"value": 0.16650000000000004, "phi": null, "theta": null, "reading_index_phi": null, "reading_index_theta": null, "is_valid": true, "id": 2, "temperature": 34.32000000000001}, {"value": 0.2085, "phi": null, "theta": null, "reading_index_phi": null, "reading_index_theta": null, "is_valid": true, "id": 3, "temperature": 34.48500000000001}, {"value": 0.13350000000000004, "phi": null, "theta": null, "reading_index_phi": null, "reading_index_theta": null, "is_valid": true, "id": 4, "temperature": 34.650000000000006}, {"value": 0.18100000000000005, "phi": null, "theta": null, "reading_index_phi": null, "reading_index_theta": null, "is_valid": true, "id": 5, "temperature": 34.540000000000006}, {"value": 0.18750000000000006, "phi": null, "theta": null, "reading_index_phi": null, "reading_index_theta": null, "is_valid": true, "id": 6, "temperature": 34.430000000000014}, {"value": 0.179, "phi": null, "theta": null, "reading_index_phi": null, "reading_index_theta": null, "is_valid": true, "id": 7, "temperature": 34.48500000000001}, {"value": 0.18400000000000002, "phi": null, "theta": null, "reading_index_phi": null, "reading_index_theta": null, "is_valid": true, "id": 8, "temperature": 34.54000000000001}, {"value": 0.11750000000000005, "phi": null, "theta": null, "reading_index_phi": null, "reading_index_theta": null, "is_valid": true, "id": 9, "temperature": 34.485000000000014}, {"value": 0.15300000000000002, "phi": null, "theta": null, "reading_index_phi": null, "reading_index_theta": null, "is_valid": true, "id": 10, "temperature": 34.59500000000001}, {"value": 0.1275, "phi": null, "theta": null, "reading_index_phi": null, "reading_index_theta": null, "is_valid": true, "id": 11, "temperature": 34.485}, {"value": 0.13499999999999998, "phi": null, "theta": null, "reading_index_phi": null, "reading_index_theta": null, "is_valid": true, "id": 12, "temperature": 34.43000000000001}, {"value": 0.14100000000000001, "phi": null, "theta": null, "reading_index_phi": null, "reading_index_theta": null, "is_valid": true, "id": 13, "temperature": 34.43000000000001}, {"value": 0.14200000000000002, "phi": null, "theta": null, "reading_index_phi": null, "reading_index_theta": null, "is_valid": true, "id": 14, "temperature": 34.540000000000006}, {"value": 0.13100000000000003, "phi": null, "theta": null, "reading_index_phi": null, "reading_index_theta": null, "is_valid": true, "id": 15, "temperature": 34.540000000000006}, {"value": 0.19050000000000006, "phi": null, "theta": null, "reading_index_phi": null, "reading_index_theta": null, "is_valid": true, "id": 16, "temperature": 34.705000000000005}, {"value": 0.0775, "phi": null, "theta": null, "reading_index_phi": null, "reading_index_theta": null, "is_valid": true, "id": 17, "temperature": 34.48500000000001}, {"value": 0.16250000000000006, "phi": null, "theta": null, "reading_index_phi": null, "reading_index_theta": null, "is_valid": true, "id": 18, "temperature": 34.65000000000001}, {"value": 0.098, "phi": null, "theta": null, "reading_index_phi": null, "reading_index_theta": null, "is_valid": true, "id": 19, "temperature": 34.430000000000014}, {"value": 0.1955, "phi": null, "theta": null, "reading_index_phi": null, "reading_index_theta": null, "is_valid": true, "id": 20, "temperature": 34.650000000000006}, {"value": 0.0465, "phi": null, "theta": null, "reading_index_phi": null, "reading_index_theta": null, "is_valid": true, "id": 21, "temperature": 34.48500000000001}, {"value": 0.171, "phi": null, "theta": null, "reading_index_phi": null, "reading_index_theta": null, "is_valid": true, "id": 22, "temperature": 34.210000000000015}, {"value": 0.05800000000000001, "phi": null, "theta": null, "reading_index_phi": null, "reading_index_theta": null, "is_valid": true, "id": 23, "temperature": 34.210000000000015}, {"value": 0.1265, "phi": null, "theta": null, "reading_index_phi": null, "reading_index_theta": null, "is_valid": true, "id": 24, "temperature": 34.48500000000001}, {"value": 0.194, "phi": null, "theta": null, "reading_index_phi": null, "reading_index_theta": null, "is_valid": true, "id": 25, "temperature": 34.430000000000014}, {"value": 0.18850000000000003, "phi": null, "theta": null, "reading_index_phi": null, "reading_index_theta": null, "is_valid": true, "id": 26, "temperature": 34.81500000000001}, {"value": 0.11850000000000002, "phi": null, "theta": null, "reading_index_phi": null, "reading_index_theta": null, "is_valid": true, "id": 27, "temperature": 34.26500000000001}, {"value": 0.12349999999999998, "phi": null, "theta": null, "reading_index_phi": null, "reading_index_theta": null, "is_valid": true, "id": 28, "temperature": 34.32000000000001}, {"value": 0.18300000000000005, "phi": null, "theta": null, "reading_index_phi": null, "reading_index_theta": null, "is_valid": true, "id": 29, "temperature": 34.70500000000001}, {"value": 0.20799999999999996, "phi": null, "theta": null, "reading_index_phi": null, "reading_index_theta": null, "is_valid": true, "id": 30, "temperature": 34.70500000000001}, {"value": 0.13400000000000004, "phi": null, "theta": null, "reading_index_phi": null, "reading_index_theta": null, "is_valid": true, "id": 31, "temperature": 34.650000000000006}, {"value": 0.15850000000000003, "phi": null, "theta": null, "reading_index_phi": null, "reading_index_theta": null, "is_valid": true, "id": 32, "temperature": 34.76000000000001}, {"value": 0.21500000000000002, "phi": null, "theta": null, "reading_index_phi": null, "reading_index_theta": null, "is_valid": true, "id": 33, "temperature": 34.65000000000001}, {"value": 0.198, "phi": null, "theta": null, "reading_index_phi": null, "reading_index_theta": null, "is_valid": true, "id": 34, "temperature": 34.650000000000006}, {"value": 0.06650000000000003, "phi": null, "theta": null, "reading_index_phi": null, "reading_index_theta": null, "is_valid": true, "id": 35, "temperature": 34.59500000000001}, {"value": 0.11099999999999999, "phi": null, "theta": null, "reading_index_phi": null, "reading_index_theta": null, "is_valid": true, "id": 36, "temperature": 34.32000000000001}, {"value": 0.0765, "phi": null, "theta": null, "reading_index_phi": null, "reading_index_theta": null, "is_valid": true, "id": 37, "temperature": 34.10000000000001}, {"value": 0.1035, "phi": null, "theta": null, "reading_index_phi": null, "reading_index_theta": null, "is_valid": true, "id": 38, "temperature": 34.32000000000001}, {"value": 0.23100000000000004, "phi": null, "theta": null, "reading_index_phi": null, "reading_index_theta": null, "is_valid": true, "id": 39, "temperature": 34.32000000000001}, {"value": 0.15650000000000003, "phi": null, "theta": null, "reading_index_phi": null, "reading_index_theta": null, "is_valid": true, "id": 40, "temperature": 34.76000000000001}, {"value": 0.05800000000000001, "phi": null, "theta": null, "reading_index_phi": null, "reading_index_theta": null, "is_valid": true, "id": 41, "temperature": 34.54000000000001}, {"value": 0.1385, "phi": null, "theta": null, "reading_index_phi": null, "reading_index_theta": null, "is_valid": true, "id": 42, "temperature": 34.48500000000001}, {"value": 0.093, "phi": null, "theta": null, "reading_index_phi": null, "reading_index_theta": null, "is_valid": true, "id": 43, "temperature": 34.37500000000001}, {"value": 0.013999999999999995, "phi": null, "theta": null, "reading_index_phi": null, "reading_index_theta": null, "is_valid": true, "id": 44, "temperature": 34.32000000000001}, {"value": 0.16600000000000006, "phi": null, "theta": null, "reading_index_phi": null, "reading_index_theta": null, "is_valid": true, "id": 45, "temperature": 34.32000000000001}, {"value": 0.19600000000000004, "phi": null, "theta": null, "reading_index_phi": null, "reading_index_theta": null, "is_valid": true, "id": 46, "temperature": 34.32000000000001}, {"value": 0.13799999999999998, "phi": null, "theta": null, "reading_index_phi": null, "reading_index_theta": null, "is_valid": true, "id": 47, "temperature": 34.26500000000001}, {"value": 0.09199999999999998, "phi": null, "theta": null, "reading_index_phi": null, "reading_index_theta": null, "is_valid": true, "id": 48, "temperature": 34.43000000000001}, {"value": 0.15050000000000002, "phi": null, "theta": null, "reading_index_phi": null, "reading_index_theta": null, "is_valid": true, "id": 49, "temperature": 34.430000000000014}, {"value": 0.09100000000000001, "phi": null, "theta": null, "reading_index_phi": null, "reading_index_theta": null, "is_valid": true, "id": 50, "temperature": 34.26500000000001}, {"value": 0.17250000000000001, "phi": null, "theta": null, "reading_index_phi": null, "reading_index_theta": null, "is_valid": true, "id": 51, "temperature": 34.705000000000005}, {"value": 0.17650000000000002, "phi": null, "theta": null, "reading_index_phi": null, "reading_index_theta": null, "is_valid": true, "id": 52, "temperature": 34.59500000000001}, {"value": 0.08449999999999999, "phi": null, "theta": null, "reading_index_phi": null, "reading_index_theta": null, "is_valid": true, "id": 53, "temperature": 34.375000000000014}, {"value": 0.0865, "phi": null, "theta": null, "reading_index_phi": null, "reading_index_theta": null, "is_valid": true, "id": 54, "temperature": 34.70500000000001}, {"value": 0.20000000000000004, "phi": null, "theta": null, "reading_index_phi": null, "reading_index_theta": null, "is_valid": true, "id": 55, "temperature": 34.37500000000001}, {"value": 0.0965, "phi": null, "theta": null, "reading_index_phi": null, "reading_index_theta": null, "is_valid": true, "id": 56, "temperature": 34.15500000000001}, {"value": 0.094, "phi": null, "theta": null, "reading_index_phi": null, "reading_index_theta": null, "is_valid": true, "id": 57, "temperature": 34.430000000000014}, {"value": 0.1275, "phi": null, "theta": null, "reading_index_phi": null, "reading_index_theta": null, "is_valid": true, "id": 58, "temperature": 34.32000000000001}, {"value": 0.097, "phi": null, "theta": null, "reading_index_phi": null, "reading_index_theta": null, "is_valid": true, "id": 59, "temperature": 34.37500000000001}, {"value": 0.17350000000000004, "phi": null, "theta": null, "reading_index_phi": null, "reading_index_theta": null, "is_valid": true, "id": 60, "temperature": 34.15500000000001}, {"value": 0.15500000000000005, "phi": null, "theta": null, "reading_index_phi": null, "reading_index_theta": null, "is_valid": true, "id": 61, "temperature": 34.32000000000001}, {"value": 0.18050000000000005, "phi": null, "theta": null, "reading_index_phi": null, "reading_index_theta": null, "is_valid": true, "id": 62, "temperature": 34.705000000000005}, {"value": 0.21100000000000008, "phi": null, "theta": null, "reading_index_phi": null, "reading_index_theta": null, "is_valid": true, "id": 63, "temperature": 34.21000000000001}, {"value": 0.25000000000000006, "phi": null, "theta": null, "reading_index_phi": null, "reading_index_theta": null, "is_valid": true, "id": 64, "temperature": 34.59500000000001}, {"value": 0.15300000000000002, "phi": null, "theta": null, "reading_index_phi": null, "reading_index_theta": null, "is_valid": true, "id": 65, "temperature": 34.59500000000001}, {"value": 0.17850000000000005, "phi": null, "theta": null, "reading_index_phi": null, "reading_index_theta": null, "is_valid": true, "id": 66, "temperature": 34.48500000000001}, {"value": 0.16, "phi": null, "theta": null, "reading_index_phi": null, "reading_index_theta": null, "is_valid": true, "id": 67, "temperature": 34.54000000000001}, {"value": 0.17250000000000001, "phi": null, "theta": null, "reading_index_phi": null, "reading_index_theta": null, "is_valid": true, "id": 68, "temperature": 34.540000000000006}, {"value": 0.11850000000000001, "phi": null, "theta": null, "reading_index_phi": null, "reading_index_theta": null, "is_valid": true, "id": 69, "temperature": 34.81500000000001}, {"value": 0.05, "phi": null, "theta": null, "reading_index_phi": null, "reading_index_theta": null, "is_valid": true, "id": 70, "temperature": 34.59500000000001}, {"value": 0.12600000000000006, "phi": null, "theta": null, "reading_index_phi": null, "reading_index_theta": null, "is_valid": true, "id": 71, "temperature": 34.48500000000001}, {"value": 0.10699999999999998, "phi": null, "theta": null, "reading_index_phi": null, "reading_index_theta": null, "is_valid": true, "id": 72, "temperature": 34.48500000000002}, {"value": 0.12450000000000003, "phi": null, "theta": null, "reading_index_phi": null, "reading_index_theta": null, "is_valid": true, "id": 73, "temperature": 34.485}, {"value": 0.11499999999999999, "phi": null, "theta": null, "reading_index_phi": null, "reading_index_theta": null, "is_valid": true, "id": 74, "temperature": 34.595000000000006}, {"value": 0.1105, "phi": null, "theta": null, "reading_index_phi": null, "reading_index_theta": null, "is_valid": true, "id": 75, "temperature": 34.32000000000001}, {"value": 0.14600000000000002, "phi": null, "theta": null, "reading_index_phi": null, "reading_index_theta": null, "is_valid": true, "id": 76, "temperature": 34.15500000000001}, {"value": 0.19850000000000004, "phi": null, "theta": null, "reading_index_phi": null, "reading_index_theta": null, "is_valid": true, "id": 77, "temperature": 34.375000000000014}, {"value": 0.17400000000000004, "phi": null, "theta": null, "reading_index_phi": null, "reading_index_theta": null, "is_valid": true, "id": 78, "temperature": 34.485000000000014}, {"value": 0.153, "phi": null, "theta": null, "reading_index_phi": null, "reading_index_theta": null, "is_valid": true, "id": 79, "temperature": 34.65000000000001}, {"value": 0.099, "phi": null, "theta": null, "reading_index_phi": null, "reading_index_theta": null, "is_valid": true, "id": 80, "temperature": 34.100000000000016}, {"value": 0.14450000000000005, "phi": null, "theta": null, "reading_index_phi": null, "reading_index_theta": null, "is_valid": true, "id": 81, "temperature": 34.26500000000001}, {"value": 0.07, "phi": null, "theta": null, "reading_index_phi": null, "reading_index_theta": null, "is_valid": true, "id": 82, "temperature": 34.21}, {"value": 0.07949999999999999, "phi": null, "theta": null, "reading_index_phi": null, "reading_index_theta": null, "is_valid": true, "id": 83, "temperature": 34.32000000000001}, {"value": 0.17900000000000002, "phi": null, "theta": null, "reading_index_phi": null, "reading_index_theta": null, "is_valid": true, "id": 84, "temperature": 34.32000000000001}, {"value": 0.16249999999999998, "phi": null, "theta": null, "reading_index_phi": null, "reading_index_theta": null, "is_valid": true, "id": 85, "temperature": 34.26500000000001}, {"value": 0.14450000000000002, "phi": null, "theta": null, "reading_index_phi": null, "reading_index_theta": null, "is_valid": true, "id": 86, "temperature": 34.540000000000006}, {"value": 0.17900000000000002, "phi": null, "theta": null, "reading_index_phi": null, "reading_index_theta": null, "is_valid": true, "id": 87, "temperature": 34.54000000000001}, {"value": 0.18750000000000006, "phi": null, "theta": null, "reading_index_phi": null, "reading_index_theta": null, "is_valid": true, "id": 88, "temperature": 34.10000000000001}, {"value": 0.17550000000000002, "phi": null, "theta": null, "reading_index_phi": null, "reading_index_theta": null, "is_valid": true, "id": 89, "temperature": 34.375}, {"value": 0.0985, "phi": null, "theta": null, "reading_index_phi": null, "reading_index_theta": null, "is_valid": true, "id": 90, "temperature": 34.48500000000001}, {"value": 0.12350000000000001, "phi": null, "theta": null, "reading_index_phi": null, "reading_index_theta": null, "is_valid": true, "id": 91, "temperature": 34.540000000000006}, {"value": 0.14850000000000002, "phi": null, "theta": null, "reading_index_phi": null, "reading_index_theta": null, "is_valid": true, "id": 92, "temperature": 34.045}, {"value": 0.13000000000000003, "phi": null, "theta": null, "reading_index_phi": null, "reading_index_theta": null, "is_valid": true, "id": 93, "temperature": 34.26500000000001}, {"value": 0.099, "phi": null, "theta": null, "reading_index_phi": null, "reading_index_theta": null, "is_valid": true, "id": 94, "temperature": 34.21000000000001}, {"value": 0.10699999999999998, "phi": null, "theta": null, "reading_index_phi": null, "reading_index_theta": null, "is_valid": true, "id": 95, "temperature": 34.485000000000014}, {"value": 0.054000000000000006, "phi": null, "theta": null, "reading_index_phi": null, "reading_index_theta": null, "is_valid": true, "id": 96, "temperature": 34.54000000000001}, {"value": 0.14850000000000002, "phi": null, "theta": null, "reading_index_phi": null, "reading_index_theta": null, "is_valid": true, "id": 97, "temperature": 34.210000000000015}, {"value": 0.09000000000000001, "phi": null, "theta": null, "reading_index_phi": null, "reading_index_theta": null, "is_valid": true, "id": 98, "temperature": 34.48500000000001}, {"value": 0.14950000000000002, "phi": null, "theta": null, "reading_index_phi": null, "reading_index_theta": null, "is_valid": true, "id": 99, "temperature": 34.59500000000001}], "measurement_config": {"id": "525771256544952", "n_phi": 36, "n_theta": 18, "theta_radians": 3.141592653589793, "phi_radians": 6.283185307179586, "sensor_distance_radius": 1.0, "sensor_id": 0, "magnet_type": 0}, "name": "calibrationtemp30_ID:525771256544952_SID:0_MAG:NOT_SPECIFIED.mag.json", "SENSOR_SERIAL_DEVICE_PATH": "/dev/cu.usbmodem3867315334391", "SENSOR_SERIAL_NAME": "Unified Sensor 386731533439", "CONFIG_NAME": "", "READING_PREFIX": "calibrationtemp30", "READING_OUTPUT_FOLDER": "/Users/marcelochsendorf/Downloads/MagneticReadoutProcessing/src/MagneticReadoutProcessing/cli/", "READING_DATAPOINT_COUNT": "100", "READING_AVERAGE_COUNT": "20", "READING_MAGNET_TYPE": "0", "configname": "testcfg", "runner": "cli", "sensor_capabilities": "['static', 'axis_b', 'axis_x', 'axis_y', 'axis_z', 'axis_temp', 'axis_stimestamp']", "export_filepath": "/Users/marcelochsendorf/Downloads/MagneticReadoutProcessing/src/MagneticReadoutProcessing/cli//calibrationtemp30_ID:525771256544952_SID:0_MAG:NOT_SPECIFIED.mag.json", "export_filename": "calibrationtemp30_ID:525771256544952_SID:0_MAG:NOT_SPECIFIED.mag.json"}